table_builder_io/__init__.py
table_builder_io/parse_metadata.py
table_builder_io/reader.py
table_builder_io/regexes.py
table_builder_io-0.2.0.dist-info/LICENSE
table_builder_io-0.2.0.dist-info/WHEEL
table_builder_io-0.2.0.dist-info/METADATA
table_builder_io-0.2.0.dist-info/RECORD
