Metadata-Version: 2.1
Name: table_builder_io
Version: 0.2.0
Summary: Tool for reading ABS TableBuilder datasets easily in Python.
Author-email: Matt Richards <matt.richards@veitchlister.com>, Veitch Lister Consulting <developers@veitchlister.com>
Requires-Python: >=3.6
Classifier: License :: OSI Approved :: MIT License
Classifier: Operating System :: OS Independent
Classifier: Programming Language :: Python :: 3
Requires-Dist: pandas >=1.0
Requires-Dist: typing_extensions
Requires-Dist: dataclasses; python_version == '3.6'
Project-URL: Home, https://github.com/vlc/table_builder_io
